siibra/VERSION
siibra/__init__.py
siibra/commons.py
siibra/exceptions.py
siibra/configuration/__init__.py
siibra/configuration/configuration.py
siibra/configuration/factory.py
siibra/core/__init__.py
siibra/core/assignment.py
siibra/core/atlas.py
siibra/core/concept.py
siibra/core/parcellation.py
siibra/core/region.py
siibra/core/space.py
siibra/core/structure.py
siibra/experimental/__init__.py
siibra/experimental/contour.py
siibra/experimental/cortical_profile_sampler.py
siibra/experimental/patch.py
siibra/experimental/plane3d.py
siibra/explorer/__init__.py
siibra/explorer/url.py
siibra/explorer/util.py
siibra/features/__init__.py
siibra/features/anchor.py
siibra/features/feature.py
siibra/features/connectivity/__init__.py
siibra/features/connectivity/functional_connectivity.py
siibra/features/connectivity/regional_connectivity.py
siibra/features/connectivity/streamline_counts.py
siibra/features/connectivity/streamline_lengths.py
siibra/features/connectivity/tracing_connectivity.py
siibra/features/dataset/__init__.py
siibra/features/dataset/ebrains.py
siibra/features/image/__init__.py
siibra/features/image/image.py
siibra/features/image/sections.py
siibra/features/image/volume_of_interest.py
siibra/features/tabular/__init__.py
siibra/features/tabular/bigbrain_intensity_profile.py
siibra/features/tabular/cell_density_profile.py
siibra/features/tabular/cortical_profile.py
siibra/features/tabular/gene_expression.py
siibra/features/tabular/layerwise_bigbrain_intensities.py
siibra/features/tabular/layerwise_cell_density.py
siibra/features/tabular/receptor_density_fingerprint.py
siibra/features/tabular/receptor_density_profile.py
siibra/features/tabular/regional_timeseries_activity.py
siibra/features/tabular/tabular.py
siibra/livequeries/__init__.py
siibra/livequeries/allen.py
siibra/livequeries/bigbrain.py
siibra/livequeries/ebrains.py
siibra/livequeries/query.py
siibra/locations/__init__.py
siibra/locations/boundingbox.py
siibra/locations/location.py
siibra-1.0a19.dist-info/LICENSE
siibra-1.0a19.dist-info/METADATA
siibra-1.0a19.dist-info/WHEEL
siibra-1.0a19.dist-info/top_level.txt
siibra-1.0a19.dist-info/RECORD
