Metadata-Version: 2.1
Name: siibra
Version: 1.0a19
Summary: siibra - Software interfaces for interacting with brain atlases
Home-page: https://github.com/FZJ-INM1-BDA/siibra-python
Author: Big Data Analytics Group, Forschungszentrum Juelich, Institute of Neuroscience and Medicine (INM-1)
Author-email: inm1-bda@fz-juelich.de
Classifier: Development Status :: 2 - Pre-Alpha
Classifier: Programming Language :: Python :: 3.7
Classifier: Programming Language :: Python :: 3.8
Classifier: Programming Language :: Python :: 3.9
Classifier: Programming Language :: Python :: 3.10
Classifier: Programming Language :: Python :: 3.11
Classifier: Programming Language :: Python :: 3.12
Classifier: Operating System :: OS Independent
Classifier: Intended Audience :: Developers
Requires-Python: >=3.7
License-File: LICENSE
Requires-Dist: anytree
Requires-Dist: nibabel
Requires-Dist: appdirs
Requires-Dist: scikit-image
Requires-Dist: requests
Requires-Dist: neuroglancer-scripts
Requires-Dist: nilearn
Requires-Dist: filelock
Requires-Dist: ebrains-drive>=0.6.0
Requires-Dist: typing-extensions; python_version < "3.8"
